{"branch":"arkcraft:expansion","name":"Expansion: Ayuntamiento IV","subtitle":"Tributo: 9 monedas de esmeralda","icon":"minecolonies:blockhuttownhall","costs":[{"count":9,"item":"lightmanscurrency:coin_emerald"}],"effects":[{"id":"minecolonies:effects/blockhuttownhall","level":4}],"requirements":[{"type":"minecolonies:research","research":"arkcraft:expansion/townhall3"},{"type":"minecolonies:single-building","building":"minecolonies:townhall","level":3},{"type":"minecolonies:single-building","building":"minecolonies:university","level":2}],"researchLevel":1,"sortOrder":1}
